setup.py
distributions51/Binomialdistribution.py
distributions51/Gaussiandistribution.py
distributions51/Generaldistribution.py
distributions51/__init__.py
distributions51.egg-info/PKG-INFO
distributions51.egg-info/SOURCES.txt
distributions51.egg-info/dependency_links.txt
distributions51.egg-info/not-zip-safe
distributions51.egg-info/top_level.txt